{
  "project_info": {
    "project_number": "55163426810",
    "project_id": "homezes-flutter-app",
    "storage_bucket": "homezes-flutter-app.firebasestorage.app"
  },
  "client": [
    {
      "client_info": {
        "mobilesdk_app_id": "1:55163426810:android:5a17d48b34cee2b386f643",
        "android_client_info": {
          "package_name": "com.example.homzes_app"
        }
      },
      "oauth_client": [],
      "api_key": [
        {
          "current_key": "AIzaSyAyfpCLPwK-JzHaV0TZdBns5RrFWG9x-oE"
        }
      ],
      "services": {
        "appinvite_service": {
          "other_platform_oauth_client": []
        }
      }
    }
  ],
  "configuration_version": "1"
}